{
  "vers": "1.0",
  "coorSys": "",
  "dataset":{
    "ds1": {
      "type":2,
      "priority":1,
      "url":"WellLogDataParser/CurveData",
      "params":{
        "file": "",
        "curveName":""
      }
    }
  },
  "seriesMapping":[
    {
      "source":"ds1",
      "seriesName": "SW2-1井-测井解释图"
    }
  ],
  "series": [
    {
      "name":"SW2-1井-测井解释图",
      "type":"wellLogging",
      "top": 20,
      "scale": 500,
      "depth": [800, 2250],

      "itemStyle": {
        "header":{
          "borderWidth": 1
        },
        "title":{
          "show": true,
          "borderWidth": 0,
          "textStyle":{
            "fontSize": 25
          }
        }
      },
      "data":[{
        "type": "track",
        "name": "孔隙度",
        "width": 150,
        "children": [
          {
            "type": "curve",
            "name": "AC",
            "aliasName": "声波时差",
            "scaleType": "lin",
            "leftScale": 100,
            "rightScale": 350,
            "secondScale": -1,

            "curveFills":[{
              "name": "",
              "fillTo":"left",
              "fillStyle": "green"
            }],
            "itemStyle": {
            },
            "lineStyle":{
              "color": "red",
              "width": 2,
              "type": "solid"
            },
            "data": []
          }
        ]
      },
        {
          "type": "track",
          "name": "孔隙度",
          "width": 150,
          "children": [
            {
              "type": "curve",
              "name": "AC",
              "aliasName": "声波时差",
              "scaleType": "lin",
              "leftScale": 100,
              "rightScale": 350,
              "secondScale": 0,
              "headerFill":{
                "textStyle":{
                  "color": "red"
                }
              },
              "curveFills":[{
                "name": "",
                "fillTo":"left",
                "fillStyle": {
                  "type": "linear",
                  "x": 0,
                  "y": 0,
                  "x2": 1,
                  "y2": 0,
                  "colorStops": [{
                  "offset": 0, "color": "red"
                  }, {
                    "offset": 1, "color": "blue"
                  }],
                  "global": false
                }
              }],
              "itemStyle": {
              },
              "lineStyle":{
                "color": "red",
                "width": 2,
                "type": "solid"
              },
              "data": []
            }
          ]
        },
        {
          "type": "track",
          "name": "孔隙度",
          "width": 150,
          "children": [
            {
              "type": "curve",
              "name": "AC",
              "aliasName": "声波时差",
              "unit": "cm",
              "scaleType": "lin",
              "leftScale": 100,
              "rightScale": 350,
              "secondScale": 0,
              "curveFills":[{
                "name": "11",
                "fillTo":"left",
                "fillStyle": "WCJW-CCB0022H"
              },{
                "name": "22",
                "fillTo":"right",
                "fillStyle": "WCJW-CCB0022M"
              }],
              "itemStyle": {
              },
              "lineStyle":{
                "color": "blue",
                "width": 2,
                "type": "solid"
              },
              "data": []
            }

          ]
        }
      ]
    }
  ],
  "fonts":{
    "1": {
      "fontFamily": "Arial",
      "fontStyle": "normal",
      "fontSize": "40px",
      "fontColor": "#000000",
      "fontWeight": "bold",
      "textAlign": "left",
      "textVerticalAlign": "middle",
      "textRotation": "0"
    },
    "2": {
      "fontFamily": "Georgia",
      "fontStyle": "normal",
      "fontSize": "12px",
      "fontColor": "#000000",
      "fontWeight": "normal",
      "textAlign": "left",
      "textVerticalAlign": "middle",
      "textRotation": "0"
    },
    "3": {
      "fontFamily": "serif",
      "fontStyle": "normal",
      "fontSize": "9px",
      "fontColor": "#000000",
      "fontWeight": "normal",
      "textAlign": "left",
      "textVerticalAlign": "middle",
      "textRotation": "0"
    }
  }

}
